dero/__init__.py
dero/compustat.py
dero/config.py
dero/core.py
dero/data.py
dero/decorators.py
dero/dropbox.py
dero/ext_logging.py
dero/ext_math.py
dero/ext_matplotlib.py
dero/ext_multiprocessing.py
dero/ext_pandas.py
dero/ext_selenium.py
dero/ext_sympy.py
dero/ext_time.py
dero/latex.py
dero/logging.py
dero/logtimer.py
dero/matplotlib.py
dero/multiprocessing.py
dero/pandas.py
dero/pdf.py
dero/pdutils.py
dero/reg.py
dero/selenium.py
dero/setup.py
dero/summ.py
dero/sympy.py
dero/time.py
dero/version.py
dero/wrds.py
dero/data/__init__.py
dero/data/typing.py
dero/data/compareids/__init__.py
dero/data/compareids/backend.py
dero/data/compareids/tools.py
dero/data/compareids/frontends/__init__.py
dero/data/compareids/frontends/text_summ.py
dero/data/compareids/models/__init__.py
dero/data/compareids/models/bars.py
dero/data/compareids/models/base.py
dero/data/compareids/models/datasets.py
dero/data/compareids/models/flowchart.py
dero/data/compareids/models/interface.py
dero/data/compareids/models/main.py
dero/data/compareids/models/steps.py
dero/data/display/__init__.py
dero/data/ff/__init__.py
dero/data/ff/fftypes.py
dero/data/ff/create/__init__.py
dero/data/ff/create/average.py
dero/data/ff/create/dualsort.py
dero/data/ff/create/inputs.py
dero/data/ff/create/label.py
dero/data/ff/create/main.py
dero/data/ff/create/mainport.py
dero/data/ff/create/minus.py
dero/data/ff/create/model.py
dero/data/ff/create/reshape.py
dero/data/ff/create/sort.py
dero/data/formatters/__init__.py
dero/data/formatters/stars.py
dero/data/formatters/stderr.py
dero/data/formatters/models/__init__.py
dero/data/formatters/models/result.py
dero/data/panel/__init__.py
dero/data/panel/expandselect.py
dero/data/panel/did/__init__.py
dero/data/panel/did/dataprep.py
dero/data/panel/did/main.py
dero/data/panel/did/reg.py
dero/data/panel/did/totex.py
dero/data/portfolio/__init__.py
dero/data/portfolio/name.py
dero/data/portfolio/resample.py
dero/data/portfolio/sort.py
dero/data/portfolio/typing.py
Dero-0.15.0.dist-info/LICENSE.txt
Dero-0.15.0.dist-info/METADATA
Dero-0.15.0.dist-info/WHEEL
Dero-0.15.0.dist-info/top_level.txt
Dero-0.15.0.dist-info/RECORD
